dramatiq_sqlite/__init__.py
dramatiq_sqlite-0.1.0.dist-info/WHEEL
dramatiq_sqlite-0.1.0.dist-info/METADATA
dramatiq_sqlite-0.1.0.dist-info/RECORD
