Metadata-Version: 2.4
Name: dramatiq-sqlite
Version: 0.1.0
Summary: SQLite backend for Dramatiq
Author: Maxime Bouroumeau-Fuseau
Author-email: Maxime Bouroumeau-Fuseau <maxime.bouroumeau@gmail.com>
License-Expression: MIT
Requires-Dist: dramatiq>=1.18
Requires-Python: >=3.10
Project-URL: Repository, https://github.com/hyperflask/dramatiq-sqlite
